README
setup.py
test/test_applyMacros.py
test/test_common.py
test/test_filterer.py
test/test_tags.py
test/test_tiddler.py
test/test_tiddlers.py
test/test_views.py
tiddlywebplugins/__init__.py
tiddlywebplugins/wikklytextrender.py
tiddlywebplugins.wikklytextplugins.egg-info/PKG-INFO
tiddlywebplugins.wikklytextplugins.egg-info/SOURCES.txt
tiddlywebplugins.wikklytextplugins.egg-info/dependency_links.txt
tiddlywebplugins.wikklytextplugins.egg-info/namespace_packages.txt
tiddlywebplugins.wikklytextplugins.egg-info/not-zip-safe
tiddlywebplugins.wikklytextplugins.egg-info/top_level.txt
tiddlywebplugins/wikklytextplugins/__init__.py
tiddlywebplugins/wikklytextplugins/filterer.py
tiddlywebplugins/wikklytextplugins/plugins/__init__.py
tiddlywebplugins/wikklytextplugins/plugins/macros/__init__.py