Metadata-Version: 1.0
Name: tiddlywebplugins.wikklytextplugins
Version: 0.551
Summary: UNKNOWN
Home-page: http://pypi.python.org/pypi/tiddlywebplugins.wikklytextplugins
Author: Jon Robson
Author-email: jdlrobson@gmail.com
License: UNKNOWN
Platform: Posix; MacOS X; Windows
